adjunct/__init__.py
adjunct/constants.py
adjunct/exceptions.py
adjunct/interpreter.py
adjunct/parser.py
adjunct/utils.py
adjunct/builtins/__init__.py
adjunct/builtins/interrupts.py
adjunct-0.1.0.dist-info/LICENSE
adjunct-0.1.0.dist-info/METADATA
adjunct-0.1.0.dist-info/WHEEL
adjunct-0.1.0.dist-info/top_level.txt
adjunct-0.1.0.dist-info/RECORD
