Metadata-Version: 2.1
Name: adjunct
Version: 0.1.0
Summary: Adjunct -- A Python DSL
Home-page: https://github.com/jbowen7/adjunct
Author: John Bowen
Author-email: jbowen7@gmail.com
License: UNKNOWN
Keywords: python,adjunct,dsl
Platform: UNKNOWN
